ar_filters/_init_.py
ar_filters/apply_filter.py
ar_filters/create_points_labels.py
ar_filters/faceBlendCommon.py
ar_filters/main2.py
ar_filters/filters/Mask.png
ar_filters/filters/Mask1.csv
ar_filters/filters/Mask_annotations.csv
ar_filters/filters/Squid-Game-Front-Man-Mask.png
ar_filters/filters/Squid-Game-Front-Man-Mask2.png
ar_filters/filters/Squid-Game-Front-Man-Mask_annotations.csv
ar_filters/filters/Squid-Game-Guard-Mask.png
ar_filters/filters/Squid-Game-Guard-Mask_annotations.csv
ar_filters/filters/anime.png
ar_filters/filters/anime_annotations.csv
ar_filters/filters/anonymous.png
ar_filters/filters/anonymous_annotations.csv
ar_filters/filters/cat-ears.png
ar_filters/filters/cat-ears_annotations.csv
ar_filters/filters/cat-nose.png
ar_filters/filters/cat-nose_annotations.csv
ar_filters/filters/dog-ears.png
ar_filters/filters/dog-ears_annotations.csv
ar_filters/filters/dog-nose.png
ar_filters/filters/dog-nose_annotations - Copy.csv
ar_filters/filters/dog-nose_annotations.csv
ar_filters/filters/dog-tongue_annotations.csv
ar_filters/filters/flower-crown.png
ar_filters/filters/flower-crown_annotations.csv
ar_filters/filters/glasses.png
ar_filters/filters/gold-crown.png
ar_filters/filters/gold-crown_annotations.csv
ar_filters/filters/green-carnival.csv
ar_filters/filters/green-carnival.png
ar_filters/filters/green-carnival_annotations.csv
ar_filters/filters/jason-joker.csv
ar_filters/filters/jason-joker.png
ar_filters/filters/jason-joker_annotations.csv
ar_filters/filters/mustache.png
ar_filters-0.0.8.dist-info/LICENSE
ar_filters-0.0.8.dist-info/METADATA
ar_filters-0.0.8.dist-info/WHEEL
ar_filters-0.0.8.dist-info/top_level.txt
ar_filters-0.0.8.dist-info/RECORD
