Metadata-Version: 2.1
Name: ar-filters
Version: 0.0.8
Summary: A small example package
Home-page: https://github.com/EricLee2021-72324/handpose_x
Author: Eric
Author-email: koke8756@qq.com
Classifier: Programming Language :: Python :: 3
Classifier: License :: OSI Approved :: MIT License
Classifier: Operating System :: OS Independent
Requires-Python: >=3.6
License-File: LICENSE
Requires-Dist: mediapipe
